<?xml version="1.0" encoding="UTF-8"?><record_update table="sp_instance">
    <sp_instance action="INSERT_OR_UPDATE">
        <active>true</active>
        <class_name/>
        <color>default</color>
        <css/>
        <glyph/>
        <id/>
        <order>1</order>
        <roles/>
        <short_description/>
        <size>md</size>
        <sp_column display_value="1">318bf7e9db1233006a0f924bdb961951</sp_column>
        <sp_widget display_value="Twilio Flex Workspace Call Module">48d0c415db6cf49039d32d89139619c5</sp_widget>
        <sys_class_name>sp_instance</sys_class_name>
        <sys_created_by>admin</sys_created_by>
        <sys_created_on>2019-06-27 21:18:33</sys_created_on>
        <sys_customer_update>false</sys_customer_update>
        <sys_id>409bbb69db1233006a0f924bdb9619f9</sys_id>
        <sys_mod_count>1</sys_mod_count>
        <sys_name/>
        <sys_package display_value="ServiceNow Twilio Integration" source="x_8725_servicenow">10e83fe1db1233006a0f924bdb961947</sys_package>
        <sys_policy/>
        <sys_replace_on_upgrade>false</sys_replace_on_upgrade>
        <sys_scope display_value="ServiceNow Twilio Integration">10e83fe1db1233006a0f924bdb961947</sys_scope>
        <sys_update_name>sp_instance_409bbb69db1233006a0f924bdb9619f9</sys_update_name>
        <sys_updated_by>vviswanathan</sys_updated_by>
        <sys_updated_on>2021-06-03 17:38:23</sys_updated_on>
        <title/>
        <url/>
        <widget_parameters/>
    </sp_instance>
    <sys_translated_text action="delete_multiple" query="documentkey=409bbb69db1233006a0f924bdb9619f9"/>
</record_update>
